Workbook

Sheet Summary
A1: Spring into Queen Creek — Budget Summary
A2: Frontier Family Park | 4-hour event | ~3,500 attendees | Revenue in black, Expenses in red
B4: Estimated | C4: Actual | D4: Variance
A5: Total Revenue | B5: ='Budget Detail'!C44 | C5: ='Budget Detail'!D44 | D5: ='Budget Detail'!E44
A6: Total Expenses | B6: ='Budget Detail'!C108 | C6: ='Budget Detail'!D108 | D6: ='Budget Detail'!E108
A7: Over / (Under) — Budget Impact | B7: ='Budget Detail'!C110 | C7: ='Budget Detail'!D110 | D7: ='Budget Detail'!E110
A10: Category Breakdown
A11: Category | B11: Estimated | C11: Actual | D11: Variance
A12: Revenue — Transfer In | B12: ='Budget Detail'!C7 | C12: ='Budget Detail'!D7 | D12: ='Budget Detail'!E7
A13: Revenue — Sponsorships | B13: ='Budget Detail'!C18 | C13: ='Budget Detail'!D18 | D13: ='Budget Detail'!E18
A14: Revenue — Food Vendors | B14: ='Budget Detail'!C36 | C14: ='Budget Detail'!D36 | D14: ='Budget Detail'!E36
A15: Revenue — Non-Profits | B15: ='Budget Detail'!C42 | C15: ='Budget Detail'!D42 | D15: ='Budget Detail'!E42
A16: Expenses — Labor Distribution | B16: ='Budget Detail'!C54 | C16: ='Budget Detail'!D54 | D16: ='Budget Detail'!E54
A17: Expenses — Equipment/Supplies | B17: ='Budget Detail'!C59 | C17: ='Budget Detail'!D59 | D17: ='Budget Detail'!E59
A18: Expenses — Entertainment/Activities | B18: ='Budget Detail'!C73 | C18: ='Budget Detail'!D73 | D18: ='Budget Detail'!E73
A19: Expenses — Marketing | B19: ='Budget Detail'!C85 | C19: ='Budget Detail'!D85 | D19: ='Budget Detail'!E85
A20: Expenses — Logistics | B20: ='Budget Detail'!C97 | C20: ='Budget Detail'!D97 | D20: ='Budget Detail'!E97
A21: Expenses — Misc. | B21: ='Budget Detail'!C106 | C21: ='Budget Detail'!D106 | D21: ='Budget Detail'!E106
A23: All figures on both sheets are live formulas referencing Budget Detail — edit any Est./Actual cell there and every subtotal, total, and this Summary sheet recalculate automatically. See the Sources tab for what's independently sourced vs. a planning estimate.

Sheet Budget Detail
A1: Spring into Queen Creek — Staffing & Budget
A2: Frontier Family Park, Queen Creek, AZ | 4-hour event, ~3,500 attendees | Revenue in black, Expenses in red | see the Sources tab for citations
A4: REVENUE — Transfer In
A5: Line Item | B5: Description | C5: Est. Amount | D5: Actual Amount | E5: Variance
A6: Prior Year Carryover | B6: No carryover budgeted for this cycle | C6: 0 | D6: 0 | E6: =D6-C6
A7: Transfer In Subtotal | C7: =SUM(C6:C6) | D7: =SUM(D6:D6) | E7: =SUM(E6:E6)
A9: REVENUE — Sponsorships
A10: Line Item | B10: Description | C10: Est. Amount | D10: Actual Amount | E10: Variance
A11: Queen Creek Olive Mill | B11: Presenting local partner — cash + tasting-experience prize | C11: 2000 | D11: 2000 | E11: =D11-C11
A12: Schnepf Farms | B12: Family day-pass prize package sponsor | C12: 2500 | D12: 2500 | E12: =D12-C12
A13: SRP | B13: Utility community sponsorship | C13: 3000 | D13: 3000 | E13: =D13-C13
A14: EPCOR Water | B14: Utility community sponsorship | C14: 2000 | D14: 2000 | E14: =D14-C14
A15: Sossaman Farms / Hayden Flour Mills | B15: Milling & baking experience prize sponsor | C15: 1500 | D15: 1500 | E15: =D15-C15
A16: Pecan Lake Entertainment | B16: Family activity package sponsor | C16: 1000 | D16: 1200 | E16: =D16-C16
A17: San Tan Flat | B17: Family dinner package sponsor | C17: 1500 | D17: 1500 | E17: =D17-C17
A18: Sponsorships Subtotal | C18: =SUM(C11:C17) | D18: =SUM(D11:D17) | E18: =SUM(E11:E17)
A20: REVENUE — Food Vendors
A21: Line Item | B21: Description | C21: Est. Amount | D21: Actual Amount | E21: Variance
A22: Dawn Breakers: Coffee and Boba | B22: Food Truck — booth fee | C22: 125 | D22: 125 | E22: =D22-C22
A23: San Tan Sweets Bakery | B23: Food Booth — booth fee | C23: 100 | D23: 100 | E23: =D23-C23
A24: Copper State BBQ | B24: Food Truck — booth fee | C24: 125 | D24: 125 | E24: =D24-C24
A25: Desert Ridge Snow Cones | B25: Food Truck — booth fee | C25: 100 | D25: 100 | E25: =D25-C25
A26: Queen Creek Kettle Corn Co. | B26: Food Booth — booth fee | C26: 75 | D26: 75 | E26: =D26-C26
A27: Sonoran Dog House | B27: Food Truck — booth fee | C27: 125 | D27: 125 | E27: =D27-C27
A28: Mesquite Grill Food Truck | B28: Food Truck — booth fee | C28: 125 | D28: 125 | E28: =D28-C28
A29: Frosty Paletas | B29: Food Truck — booth fee | C29: 100 | D29: 100 | E29: =D29-C29
A30: Cactus Flower Lemonade | B30: Food Booth — booth fee | C30: 75 | D30: 75 | E30: =D30-C30
A31: Family Bakery of Queen Creek | B31: Food Booth — booth fee (upgraded to truck spot) | C31: 100 | D31: 125 | E31: =D31-C31
A32: Loaded Nacho Co. | B32: Food Truck — booth fee | C32: 125 | D32: 125 | E32: =D32-C32
A33: Southwest Churro Cart | B33: Food Truck — booth fee | C33: 100 | D33: 100 | E33: =D33-C33
... A35: Sweet Treats Ice Cream | B35: Food Booth — booth fee | C35: 75 | D35: 75 | E35: =D35-C35
A36: Food Vendors Subtotal | C36: =SUM(C22:C35) | D36: =SUM(D22:D35) | E36: =SUM(E22:E35)
A38: REVENUE — Non-Profits
A39: Line Item | B39: Description | C39: Est. Amount | D39: Actual Amount | E39: Variance
A40: QCUSD Foundation | B40: Comped community booth per Town policy | C40: 0 | D40: 0 | E40: =D40-C40
A41: Combs High School Booster Club | B41: Discounted non-profit booth fee | C41: 50 | D41: 50 | E41: =D41-C41
A42: Non-Profits Subtotal | C42: =SUM(C40:C41) | D42: =SUM(D40:D41) | E42: =SUM(E40:E41)
A44: TOTAL REVENUE | C44: =C7+C18+C36+C42 | D44: =D7+D18+D36+D42 | E44: =E7+E18+E36+E42
A46: EXPENSES — Labor Distribution
A47: Line Item | B47: Description | C47: Est. Amount | D47: Actual Amount | E47: Variance
A48: Part-Time Staff — Recreation Aides | B48: 60 hrs x $15.75/hr | C48: 945 | D48: 945 | E48: =D48-C48
A49: Part-Time Staff — Recreation Instructors/Specialists | B49: 40 hrs x $24.00/hr | C49: 960 | D49: 960 | E49: =D49-C49
A50: Part-Time Staff — Trainees | B50: 50 hrs x $15.15/hr | C50: 757.5 | D50: 757.5 | E50: =D50-C50
A51: Part-Time Staff — Security | B51: 60 hrs x $18.00/hr | C51: 1080 | D51: 1080 | E51: =D51-C51
A52: Queen Creek High School Booster Club | B52: In-kind: event-day setup crew | C52: 500 | D52: 500 | E52: =D52-C52
A53: Combs High School Drama Club | B53: In-kind: decoration & activation | C53: 500 | D53: 500 | E53: =D53-C53
A54: Labor Distribution Subtotal | C54: =SUM(C48:C53) | D54: =SUM(D48:D53) | E54: =SUM(E48:E53)
A56: EXPENSES — Equipment/Supplies
A57: Line Item | B57: Description | C57: Est. Amount | D57: Actual Amount | E57: Variance
A58: Desert Sound & Stage | B58: Main stage audio, lighting & backline rental | C58: 2200 | D58: 2350 | E58: =D58-C58
A59: Equipment/Supplies Subtotal | C59: =SUM(C58:C58) | D59: =SUM(D58:D58) | E59: =SUM(E58:E58)
A61: EXPENSES — Entertainment/Activities
A62: Line Item | B62: Description | C62: Est. Amount | D62: Actual Amount | E62: Variance
A63: Egg Hunt Supplies | B63: 12,000 plastic eggs + Golden Ticket / Silver Egg prize inserts | C63: 1440 | D63: 1500 | E63: =D63-C63
A64: Easter Bunny Appearance | B64: Costume & appearance fee | C64: 600 | D64: 600 | E64: =D64-C64
A65: Fast & Furriest Animal Races | B65: Chick, bunny & tortoise rental + handlers, 3-hr minimum | C65: 1695 | D65: 1695 | E65: =D65-C65
A66: Play Zone Inflatables | B66: Bungee run, obstacle course, mega slides | C66: 1800 | D66: 1950 | E66: =D66-C66
A67: Tot Spot Bounce House & Soft Play | B67: Ages 5-and-under play area rental | C67: 350 | D67: 350 | E67: =D67-C67
A68: The Great EggScape | B68: Interactive story-walk props & staging | C68: 1200 | D68: 1150 | E68: =D68-C68
A69: Color Blast Supplies | B69: Splatter-paint experience materials | C69: 900 | D69: 975 | E69: =D69-C69
A70: DJ / Emcee Services | B70: Schedule announcements, race calls, drawing — 4 hrs x $150/hr | C70: 600 | D70: 600 | E70: =D70-C70
A71: Face Painting & Balloon Artists | B71: 2 roving artists, 4-hour booking | C71: 700 | D71: 700 | E71: =D71-C71
A72: Photo Backdrop & Prop Rental | B72: Post-hunt photo-op backdrop | C72: 500 | D72: 525 | E72: =D72-C72
A73: Entertainment/Activities Subtotal | C73: =SUM(C63:C72) | D73: =SUM(D63:D72) | E73: =SUM(E63:E72)
A75: EXPENSES — Marketing
A76: Line Item | B76: Description | C76: Est. Amount | D76: Actual Amount | E76: Variance
A77: Queen Creek Print Shop | B77: Event flyers (2,000) | C77: 180 | D77: 175 | E77: =D77-C77
A78: Queen Creek Print Shop | B78: Yard signs (25) | C78: 220 | D78: 230 | E78: =D78-C78
A79: Queen Creek Print Shop | B79: Vendor row banners (10) | C79: 350 | D79: 340 | E79: =D79-C79
A80: Queen Creek Print Shop | B80: Sponsor recognition signage | C80: 275 | D80: 290 | E80: =D80-C80
A81: Social Media Boost | B81: Facebook / Instagram promoted posts | C81: 300 | D81: 300 | E81: =D81-C81
A82: Queen Creek Independent | B82: Print advertisement | C82: 250 | D82: 250 | E82: =D82-C82
A83: Wristbands & Passport Cards | B83: 3,500 attendee wristbands | C83: 420 | D83: 410 | E83: =D83-C83
A84: Site Map & Directional Signage | B84: Zone signage for the main walkway | C84: 300 | D84: 315 | E84: =D84-C84
A85: Marketing Subtotal | C85: =SUM(C77:C84) | D85: =SUM(D77:D84) | E85: =SUM(E77:E84)
A87: EXPENSES — Logistics
A88: Line Item | B88: Description | C88: Est. Amount | D88: Actual Amount | E88: Variance
A89: AZ Restroom Solutions | B89: 6 standard units @ ~$150 + 1 ADA trailer @ ~$900 | C89: 1800 | D89: 1850 | E89: =D89-C89
A90: Bright Lights Generator & Light Tower Rental | B90: 2 light towers @ $150/day + 1 generator @ $120/day | C90: 450 | D90: 450 | E90: =D90-C90
A91: Queen Creek PD | B91: Traffic & security detail — 3 officers x 6 hrs x $75/hr | C91: 1350 | D91: 1350 | E91: =D91-C91
A92: Volunteer T-Shirts | B92: 150 shirts @ $6.50 | C92: 975 | D92: 975 | E92: =D92-C92
A93: Desert Cleaning Co. | B93: Janitorial services | C93: 650 | D93: 700 | E93: =D93-C93
A94: Table & Booth Covers Rental | B94: Vendor row table covers | C94: 400 | D94: 400 | E94: =D94-C94
A95: Waste & Recycling Roll-Off | B95: Post-event pickup | C95: 550 | D95: 550 | E95: =D95-C95
A96: Special Event Liability Insurance | B96: Required for Town special-event permit | C96: 500 | D96: 500 | E96: =D96-C96
A97: Logistics Subtotal | C97: =SUM(C89:C96) | D97: =SUM(D89:D96) | E97: =SUM(E89:E96)
A99: EXPENSES — Misc.
A100: Line Item | B100: Description | C100: Est. Amount | D100: Actual Amount | E100: Variance
A101: San Tan Flat | B101: Volunteer & staff lunch catering | C101: 450 | D101: 450 | E101: =D101-C101
A102: Costco | B102: Snacks & water for volunteers | C102: 300 | D102: 325 | E102: =D102-C102
A103: Home Depot | B103: Tarps & field-prep supplies | C103: 250 | D103: 260 | E103: =D103-C103
A104: First Aid & Safety Supplies | B104: Restock first-aid station | C104: 200 | D104: 200 | E104: =D104-C104
A105: Contingency / Miscellaneous | B105: Unbudgeted day-of items | C105: 500 | D105: 410 | E105: =D105-C105
A106: Misc. Subtotal | C106: =SUM(C101:C105) | D106: =SUM(D101:D105) | E106: =SUM(E101:E105)
A108: TOTAL EXPENSES | C108: =C54+C59+C73+C85+C97+C106 | D108: =D54+D59+D73+D85+D97+D106 | E108: =E54+E59+E73+E85+E97+E106
A110: OVER / (UNDER) — BUDGET IMPACT | C110: =C44-C108 | D110: =D44-D108 | E110: =E44-E108
A112: A negative Over/Under is expected for a free community event — sponsorships and vendor fees are designed to offset cost, not fully cover it. The remainder is the Town's General Fund contribution to Spring into Queen Creek. See the Sources tab for citations behind each sourced line item.

Sheet Sources
A1: Sources — Spring into Queen Creek Budget
A2: Compiled 2026-07-12 — verify rates before relying on them for a live contract
A4: Used For | B4: Finding | C4: Source
A5: Food vendor booth fees | B5: Booth fees $75-$125 depending on vendor type | C5: Town of Queen Creek 'Seeking Vendors for Spring Events' news release — queencreekaz.gov
A6: Recreation Aide part-time wage | B6: $15.75/hr, Part-Time/Seasonal | C6: Town of Queen Creek job posting, governmentjobs.com/careers/queencreek
A7: Recreation Instructor part-time wage | B7: $20.57-$28.79/hr range; midpoint ($24.00) used in Labor Distribution | C7: Town of Queen Creek job posting, governmentjobs.com/careers/queencreek
A8: Trainee wage floor | B8: Arizona state minimum wage $15.15/hr, effective 1/1/2026 | C8: Arizona Industrial Commission — azica.gov, 2026 Minimum Wage notice
A9: Off-duty / extra-duty officer rate | B9: Typical range $40-$100/hr depending on city and agency | C9: ZipRecruiter AZ off-duty officer listings; Law Enforcement Specialists Inc. pricing page (offdutypoliceofficers.com)
A10: Portable restroom rental | B10: Standard unit $100-$250/unit/weekend (Phoenix metro); ADA/luxury trailer from ~$800/weekend | C10: Canyon State Waste (canyonstatewaste.com); Arizona Portables (arizonaportables.com)
A11: Inflatable / bounce house rental | B11: Basic unit $250-$400/day; obstacle course & combo units $500-$2,500/day | C11: AZ Bounce Pro, Bounce Then Slide AZ, AZ Inflatable Events (Phoenix-metro vendors)
A12: Generator & light tower rental | B12: Light tower $75-$300/day; mid-range generator $80-$150/day | C12: RentalHawk (rentalhawk.com); RNTR generator rental cost guide (rntr.com)
A13: Petting zoo / Easter animal rental | B13: Special Easter Petting Zoo package from $1,695, 3-hr minimum | C13: A Child's Joy, Laveen AZ — achildsjoy.net
A14: Event DJ / emcee rate | B14: Typical range $100-$250/hr, avg ~$115/hr | C14: The Bash (thebash.com); Bark.com DJ pricing guide
A15: Bulk t-shirt printing | B15: $5-$8/shirt at 100+ quantity, 1-color screen print | C15: ooShirts (ooshirts.com); 4imprint bulk pricing FAQ
... A19: Marketing, equipment, and misc. line items without a web source | B19: Not independently sourced | C19: Reference: comparable line item from the provided Mesa event budget file
